setup.py
nomad_hawk/__init__.py
nomad_hawk/api_client.py
nomad_hawk/configuration.py
nomad_hawk/rest.py
nomad_hawk.egg-info/PKG-INFO
nomad_hawk.egg-info/SOURCES.txt
nomad_hawk.egg-info/dependency_links.txt
nomad_hawk.egg-info/requires.txt
nomad_hawk.egg-info/top_level.txt
nomad_hawk/api/__init__.py
nomad_hawk/api/connector_api.py
nomad_hawk/api/track_api.py
nomad_hawk/models/__init__.py
nomad_hawk/models/api_response.py
nomad_hawk/models/connector.py
nomad_hawk/models/connector_api.py
nomad_hawk/models/connector_mapping.py
nomad_hawk/models/connector_mapping_map_to.py
nomad_hawk/models/event.py
nomad_hawk/models/event_item.py
nomad_hawk/models/inline_response_200.py
test/__init__.py
test/test_api_response.py
test/test_connector.py
test/test_connector_api.py
test/test_connector_mapping.py
test/test_connector_mapping_map_to.py
test/test_event.py
test/test_inline_response_200.py
test/test_track_api.py