Metadata-Version: 1.0
Name: nomad-hawk
Version: 1.0.10
Summary: Samarkand Nomad Hawk
Home-page: https://gitlab.com/samarkand-nomad/hawk
Author: UNKNOWN
Author-email: paul@samarkand.global
License: UNKNOWN
Keywords: Swagger,Nomad Hawk
Platform: UNKNOWN
